Metadata-Version: 2.1
Name: mailer-otphero
Version: 0.0.2
Summary: Send email which scores 10/10 at mail-tester.com
Home-page: https://github.com/otphero/mailer
Author: Yakov Wildfluss
Author-email: Yakov Wildfluss <yakov@otphero.com>
Project-URL: Homepage, https://github.com/otphero/mailer
Classifier: Programming Language :: Python :: 3
Classifier: License :: OSI Approved :: MIT License
Classifier: Operating System :: OS Independent
Requires-Python: >=3.7
License-File: LICENSE
